pyaddy/API/__init__.py
pyaddy/API/addy_key.py
pyaddy/API/alias_bulk_actions.py
pyaddy/API/aliases.py
pyaddy/API/api_details.py
pyaddy/API/domain.py
pyaddy/API/url.py
pyaddy/__init__.py
pyaddy/__main__.py
pyaddy/commands/alias_bulk_actions_cmd.py
pyaddy/commands/aliases_cmd.py
pyaddy/commands/api_details_cmd.py
pyaddy/commands/domain_cmd.py
pyaddy-0.5.5.dist-info/LICENSE
pyaddy-0.5.5.dist-info/METADATA
pyaddy-0.5.5.dist-info/WHEEL
pyaddy-0.5.5.dist-info/entry_points.txt
pyaddy-0.5.5.dist-info/RECORD
