Metadata-Version: 2.1
Name: pyaddy
Version: 0.5.5
Summary: A Python package/cli to interact with addy.io
Home-page: https://github.com/msaldivar/pyaddy
License: GNU AFFERO GENERAL PUBLIC LICENSE
Author: Maurice Saldivar
Author-email: mo.py.solutions@gmail.com
Requires-Python: >=3.11,<4.0
Classifier: License :: Other/Proprietary License
Classifier: Programming Language :: Python :: 3
Classifier: Programming Language :: Python :: 3.11
Classifier: Programming Language :: Python :: 3.12
Requires-Dist: click (>=8.1.7,<9.0.0)
Requires-Dist: requests (>=2.31.0,<3.0.0)
